{
    "key": "ui_options_page_68716cc28d06d",
    "title": "Header",
    "active": true,
    "menu_order": 0,
    "page_title": "Header",
    "menu_slug": "header",
    "parent_slug": "theme-settings",
    "advanced_configuration": 0,
    "icon_url": "",
    "menu_title": "",
    "position": "",
    "redirect": false,
    "description": "",
    "menu_icon": [],
    "update_button": "Update",
    "updated_message": "Options Updated",
    "capability": "edit_posts",
    "data_storage": "options",
    "post_id": "",
    "autoload": 0,
    "modified": 1752264116
}
